kaithem_plugin_datasette/__init__.py
kaithem_plugin_datasette-0.1.2.dist-info/LICENSE
kaithem_plugin_datasette-0.1.2.dist-info/METADATA
kaithem_plugin_datasette-0.1.2.dist-info/WHEEL
kaithem_plugin_datasette-0.1.2.dist-info/top_level.txt
kaithem_plugin_datasette-0.1.2.dist-info/RECORD
