Metadata-Version: 2.2
Name: kaithem-plugin-datasette
Version: 0.1.2
Summary: Add your description here
Requires-Python: >=3.10
License-File: LICENSE
Requires-Dist: kaithem>=0.87.0
Requires-Dist: kaithem
Requires-Dist: datasette>=1.0a16
Requires-Dist: datasette-write
Requires-Dist: datasette-write-ui
Requires-Dist: datasette-edit-schema
Requires-Dist: datasette-plot
Requires-Dist: datasette-search-all
Requires-Dist: datasette-checkbox
Requires-Dist: datasette-explain
Requires-Dist: datasette-comments
Requires-Dist: datasette-render-images
Requires-Dist: datasette-render-markdown
Requires-Dist: datasette-pretty-json>=0.3
Requires-Dist: datasette-cluster-map
Requires-Dist: datasette-geojson
Requires-Dist: datasette-copyable
Requires-Dist: datasette-mp3-audio
Requires-Dist: datasette-import
